odoo8_addon_website_event_filter_selector-8.0.1.1.0.99.dev2-py2.7-nspkg.pth
odoo_addons/website_event_filter_selector/__openerp__.py
odoo_addons/website_event_filter_selector/__init__.py
odoo_addons/website_event_filter_selector/README.rst
odoo_addons/website_event_filter_selector/models/__init__.py
odoo_addons/website_event_filter_selector/models/event.py
odoo_addons/website_event_filter_selector/i18n/es.po
odoo_addons/website_event_filter_selector/i18n/de.po
odoo_addons/website_event_filter_selector/views/assets.xml
odoo_addons/website_event_filter_selector/views/templates.xml
odoo_addons/website_event_filter_selector/controllers/main.py
odoo_addons/website_event_filter_selector/controllers/__init__.py
odoo_addons/website_event_filter_selector/images/choose.png
odoo_addons/website_event_filter_selector/images/all.png
odoo_addons/website_event_filter_selector/static/description/icon.png
odoo_addons/website_event_filter_selector/static/src/js/website_event_filter_selector.js
odoo8_addon_website_event_filter_selector-8.0.1.1.0.99.dev2.dist-info/top_level.txt
odoo8_addon_website_event_filter_selector-8.0.1.1.0.99.dev2.dist-info/WHEEL
odoo8_addon_website_event_filter_selector-8.0.1.1.0.99.dev2.dist-info/RECORD
odoo8_addon_website_event_filter_selector-8.0.1.1.0.99.dev2.dist-info/metadata.json
odoo8_addon_website_event_filter_selector-8.0.1.1.0.99.dev2.dist-info/DESCRIPTION.rst
odoo8_addon_website_event_filter_selector-8.0.1.1.0.99.dev2.dist-info/METADATA
odoo8_addon_website_event_filter_selector-8.0.1.1.0.99.dev2.dist-info/namespace_packages.txt
