Metadata-Version: 2.0
Name: odoo8-addon-website-event-filter-selector
Version: 8.0.1.1.0.99.dev2
Summary: Add a customizable top area to filter events with selectors
Home-page: http://www.antiun.com
Author: UNKNOWN
Author-email: UNKNOWN
License: AGPL-3
Platform: UNKNOWN
Requires-Dist: odoo (<9.0a,>=8.0a)
Classifier: Programming Language :: Python :: 2.7
Classifier: Framework :: Odoo
Classifier: License :: OSI Approved :: GNU Affero General Public License v3
